human_cupid/__init__.py
human_cupid/cupid/__init__.py
human_cupid/cupid/cupid.py
human_cupid/cupid/schema/__init__.py
human_cupid/cupid/schema/compatibility.py
human_cupid/llm/__init__.py
human_cupid/llm/embedding.py
human_cupid/llm/llm.py
human_cupid/main.py
human_cupid/main.txt
human_cupid/sub/__init__.py
human_cupid/sub/sub.py
human_cupid/super/__init__.py
human_cupid/super/super.py
human_cupid/utils/model.py
human_cupid/utils/schemas.py
human_cupid-0.1.10.dist-info/METADATA
human_cupid-0.1.10.dist-info/WHEEL
human_cupid-0.1.10.dist-info/entry_points.txt
human_cupid-0.1.10.dist-info/RECORD
