Metadata-Version: 2.1
Name: human-cupid
Version: 0.1.10
Summary: 
Author: kithinjibrian
Author-email: kithinjibrian369@gmail.com
Requires-Python: >=3.12,<4.0
Classifier: Programming Language :: Python :: 3
Classifier: Programming Language :: Python :: 3.12
Requires-Dist: litellm (>=1.77.0,<2.0.0)
Requires-Dist: openai (>=2.9.0,<3.0.0)
Requires-Dist: pydantic (>=2.11.7,<3.0.0)
Requires-Dist: pydantic-settings (>=2.10.1,<3.0.0)
Requires-Dist: python-dotenv (>=1.1.1,<2.0.0)
